gedspy/__init__.py
gedspy/DataPrepare.py
gedspy/Enrichment.py
gedspy-2.1.9.dist-info/licenses/LICENSE
gedspy-2.1.9.dist-info/METADATA
gedspy-2.1.9.dist-info/WHEEL
gedspy-2.1.9.dist-info/RECORD
