Metadata-Version: 2.4
Name: gedspy
Version: 2.1.9
Summary: GEDSpy (Gene Enrichment for Drug Searching)
License: GPL-3
License-File: LICENSE
Keywords: RNA_seq,SEQ,GO,pathways,interactions,gene ontology,diseases,enrichment,OMIC
Author: Jakub Kubis - JBS
Author-email: jbiosystem@gmail.com
Requires-Python: >=3.12
Classifier: License :: Other/Proprietary License
Classifier: Programming Language :: Python :: 3
Classifier: Programming Language :: Python :: 3.12
Classifier: Programming Language :: Python :: 3.13
Classifier: Programming Language :: Python :: 3.14
Requires-Dist: adjusttext (>=1.0.0,<2.0.0)
Requires-Dist: beautifulsoup4 (>=4.12.0,<5.0.0)
Requires-Dist: gdown (>=5.0.0,<6.0.0)
Requires-Dist: matplotlib (>=3.8.0,<4.0.0)
Requires-Dist: networkx (>=3.0.0,<4.0.0)
Requires-Dist: numpy (>=2.0.0,<3.0.0)
Requires-Dist: pandas (>=2.0.0,<3.0.0)
Requires-Dist: pyvis (>=0.3.0,<1.0.0)
Requires-Dist: requests (>=2.0.0,<3.0.0)
Requires-Dist: scikit-learn (>=1.8.0,<2.0.0)
Requires-Dist: scipy (>=1.12.0,<2.0.0)
Requires-Dist: seaborn (>=0.13.0,<0.14.0)
Requires-Dist: setuptools (>=80.9.0,<81.0.0)
Requires-Dist: tqdm (>=4.60.0,<5.0.0)
Requires-Dist: urllib3 (>=2.0.0,<3.0.0)
Project-URL: Homepage, https://github.com/jkubis96/GEDSpy
Project-URL: Repository, https://github.com/jkubis96/GEDSpy
